devops/__init__.py
devops/cicd.py
devops/containers.py
devops/infra.py
devops/utils.py
devops_automation-0.1.0.dist-info/LICENSE
devops_automation-0.1.0.dist-info/METADATA
devops_automation-0.1.0.dist-info/WHEEL
devops_automation-0.1.0.dist-info/top_level.txt
devops_automation-0.1.0.dist-info/RECORD
