Metadata-Version: 2.1
Name: devops-automation
Version: 0.1.0
Summary: Librería para la automatización de tareas DevOps
Home-page: https://github.com/s7n5c4n/devops_automation
Author: s7n5c4n
Author-email: cr.hachim2.0@gmail.com
Classifier: Programming Language :: Python :: 3
Classifier: License :: OSI Approved :: MIT License
Classifier: Operating System :: OS Independent
Requires-Python: >=3.6
License-File: LICENSE
Requires-Dist: docker
Requires-Dist: requests
